server/__init__.py
server/__main__.py
server/__version__.py
server/auth.py
server/db.py
server/errors.py
server/logger.py
server/main.py
server/manager.py
server/models.py
server/prisma_client.py
server/process_utils.py
server/py.typed
server/repl.py
server/settings.py
server/setup.py
server/setup.sh
server/split.py
server/utils.py
server/prisma/schema.prisma
server/routers/ast.py
server/routers/backward.py
server/routers/check.py
server/routers/health.py
server/server_old/__main__.py
server/server_old/config.py
server/server_old/healthcheck.py
server/server_old/leanrepl.py
kimina_ast_server-2.1.1.dist-info/METADATA
kimina_ast_server-2.1.1.dist-info/WHEEL
kimina_ast_server-2.1.1.dist-info/entry_points.txt
kimina_ast_server-2.1.1.dist-info/licenses/LICENSE
kimina_ast_server-2.1.1.dist-info/RECORD
