Metadata-Version: 2.4
Name: kimina-ast-server
Version: 2.1.1
Summary: Kimina Lean Server - FastAPI server for checking Lean 4 code at scale
Project-URL: Homepage, https://github.com/project-numina/kimina-lean-server
Project-URL: Issues, https://github.com/project-numina/kimina-lean-server/issues
Author: Kimi Team - Project Numina
Author-email: contact@projectnumina.com
License-Expression: MIT
License-File: LICENSE
Classifier: License :: OSI Approved :: MIT License
Classifier: Operating System :: OS Independent
Classifier: Programming Language :: Python :: 3
Requires-Python: >=3.9
Requires-Dist: fastapi>=0.115.13
Requires-Dist: google-cloud-logging>=3.12.1
Requires-Dist: kimina-ast-client>=0.2.2
Requires-Dist: loguru>=0.7.3
Requires-Dist: prisma>=0.15.0
Requires-Dist: psutil>=7.0.0
Requires-Dist: pydantic-settings>=2.10.0
Requires-Dist: python-dotenv>=1.1.0
Requires-Dist: rich>=14.0.0
Requires-Dist: uvicorn>=0.34.3
